README.md
setup.cfg
setup.py
swaggeraem/__init__.py
swaggeraem/api_client.py
swaggeraem/configuration.py
swaggeraem/exceptions.py
swaggeraem/model_utils.py
swaggeraem/rest.py
swaggeraem.egg-info/PKG-INFO
swaggeraem.egg-info/SOURCES.txt
swaggeraem.egg-info/dependency_links.txt
swaggeraem.egg-info/requires.txt
swaggeraem.egg-info/top_level.txt
swaggeraem/api/__init__.py
swaggeraem/api/console_api.py
swaggeraem/api/cq_api.py
swaggeraem/api/crx_api.py
swaggeraem/api/custom_api.py
swaggeraem/api/granite_api.py
swaggeraem/api/sling_api.py
swaggeraem/apis/__init__.py
swaggeraem/apis/console_api.py
swaggeraem/apis/cq_api.py
swaggeraem/apis/crx_api.py
swaggeraem/apis/custom_api.py
swaggeraem/apis/sling_api.py
swaggeraem/model/__init__.py
swaggeraem/model/install_status.py
swaggeraem/model/install_status_status.py
swaggeraem/model/keystore_chain_items.py
swaggeraem/model/keystore_info.py
swaggeraem/model/keystore_items.py
swaggeraem/model/saml_configuration_info.py
swaggeraem/model/saml_configuration_properties.py
swaggeraem/model/saml_configuration_property_items_array.py
swaggeraem/model/saml_configuration_property_items_boolean.py
swaggeraem/model/saml_configuration_property_items_long.py
swaggeraem/model/saml_configuration_property_items_string.py
swaggeraem/model/truststore_info.py
swaggeraem/model/truststore_items.py
swaggeraem/models/__init__.py
swaggeraem/models/inline_object.py
swaggeraem/models/inline_object1.py
swaggeraem/models/inline_object2.py
swaggeraem/models/inline_object3.py
swaggeraem/models/inline_object4.py
swaggeraem/models/inline_object5.py
swaggeraem/models/install_status.py
swaggeraem/models/install_status_status.py
swaggeraem/models/keystore_chain_items.py
swaggeraem/models/keystore_info.py
swaggeraem/models/keystore_informations.py
swaggeraem/models/keystore_items.py
swaggeraem/models/saml_configuration_info.py
swaggeraem/models/saml_configuration_informations.py
swaggeraem/models/saml_configuration_properties.py
swaggeraem/models/saml_configuration_property_items_array.py
swaggeraem/models/saml_configuration_property_items_boolean.py
swaggeraem/models/saml_configuration_property_items_long.py
