Metadata-Version: 1.2
Name: swaggeraem
Version: 1.1.0
Summary: Adobe Experience Manager (AEM) API
Home-page: https://github.com/shinesolutions/swagger-aem/tree/master/python
Author: Shine Solutions
Author-email: opensource@shinesolutions.com
License: UNKNOWN
Keywords: OpenAPI,OpenAPI-Generator,Adobe Experience Manager (AEM) API
Platform: UNKNOWN
Requires-Python: >=3.6
